sparpy/__init__.py
sparpy/cli.py
sparpy/cli_options.py
sparpy/config.py
sparpy/logger.py
sparpy/plugins.py
sparpy/processor.py
sparpy/run.py
sparpy/spark.py
sparpy-0.5.5.dist-info/LICENSE
sparpy-0.5.5.dist-info/METADATA
sparpy-0.5.5.dist-info/WHEEL
sparpy-0.5.5.dist-info/entry_points.txt
sparpy-0.5.5.dist-info/top_level.txt
sparpy-0.5.5.dist-info/RECORD
