Metadata-Version: 2.1
Name: sparpy
Version: 0.5.5
Summary: A Spark entry point for python
Home-page: https://github.com/alfred82santa/sparpy
Author: Alfred Santacatalina
License: UNKNOWN
Platform: UNKNOWN
Classifier: Development Status :: 4 - Beta
Classifier: Intended Audience :: Developers
Classifier: Programming Language :: Python :: 3.6
Classifier: Programming Language :: Python :: 3.7
Requires-Dist: click
Provides-Extra: base
Requires-Dist: pkginfo ; extra == 'base'
